README.md
setup.py
npsdkk/Stockdrv.py
npsdkk/__init__.py
npsdkk/__version__.py
npsdkk/npdatapoolthread.py
npsdkk/npsdkapi.py
npsdkk/npsdkobjs.py
npsdkk.egg-info/PKG-INFO
npsdkk.egg-info/SOURCES.txt
npsdkk.egg-info/dependency_links.txt
npsdkk.egg-info/top_level.txt
npsdkk.egg-info/zip-safe